genai_colosseum/init.py
genai_colosseum/main.py
genai_colosseum/templates/chatbot/chatbot/QUICK_START.md
genai_colosseum/templates/chatbot/chatbot/README.md
genai_colosseum/templates/chatbot/chatbot/app.py
genai_colosseum/templates/chatbot/chatbot/create_venv.sh
genai_colosseum/templates/chatbot/chatbot/env_template.txt
genai_colosseum/templates/chatbot/chatbot/requirements.txt
genai_colosseum/templates/chatbot/chatbot/setup.py
genai_colosseum/templates/rag_pipeline/rag_pipeline/QUICK_START.md
genai_colosseum/templates/rag_pipeline/rag_pipeline/README.md
genai_colosseum/templates/rag_pipeline/rag_pipeline/create_venv.sh
genai_colosseum/templates/rag_pipeline/rag_pipeline/env_template.txt
genai_colosseum/templates/rag_pipeline/rag_pipeline/rag_implementation.py
genai_colosseum/templates/rag_pipeline/rag_pipeline/requirements.txt
genai_colosseum/templates/rag_pipeline/rag_pipeline/setup.py
genai_colosseum/templates/rag_pipeline/rag_pipeline/speech.txt
genai_colosseum/templates/rag_pipeline/rag_pipeline/test_embeddings.py
genai_colosseum-0.1.8.dist-info/licenses/LICENSE
genai_colosseum-0.1.8.dist-info/METADATA
genai_colosseum-0.1.8.dist-info/WHEEL
genai_colosseum-0.1.8.dist-info/entry_points.txt
genai_colosseum-0.1.8.dist-info/top_level.txt
genai_colosseum-0.1.8.dist-info/RECORD
