Metadata-Version: 2.4
Name: genai-colosseum
Version: 0.1.8
Summary: Generate and install GenAI project templates
Author-email: Your Name <your.email@example.com>
License: MIT
Requires-Python: >=3.7
License-File: LICENSE
Requires-Dist: click
Dynamic: license-file
